greetings/__init__.py
greetings/foryou.py
greetings/hackme.py
greetings/magic.py
greetingsdhruv-0.5.1.dist-info/METADATA
greetingsdhruv-0.5.1.dist-info/WHEEL
greetingsdhruv-0.5.1.dist-info/entry_points.txt
greetingsdhruv-0.5.1.dist-info/top_level.txt
greetingsdhruv-0.5.1.dist-info/RECORD
