Metadata-Version: 2.4
Name: greetingsdhruv
Version: 0.5.1
Summary: A package to pour your love in bits and bytes.
Author: Dhruv Pandey
Author-email: dhruvpandey8997@gmail.com
License: MIT
Requires-Python: >=3.7
